azure/mgmt/arizeaiobservabilityeval/__init__.py
azure/mgmt/arizeaiobservabilityeval/_client.py
azure/mgmt/arizeaiobservabilityeval/_configuration.py
azure/mgmt/arizeaiobservabilityeval/_model_base.py
azure/mgmt/arizeaiobservabilityeval/_patch.py
azure/mgmt/arizeaiobservabilityeval/_serialization.py
azure/mgmt/arizeaiobservabilityeval/_version.py
azure/mgmt/arizeaiobservabilityeval/py.typed
azure/mgmt/arizeaiobservabilityeval/_utils/__init__.py
azure/mgmt/arizeaiobservabilityeval/_utils/model_base.py
azure/mgmt/arizeaiobservabilityeval/_utils/serialization.py
azure/mgmt/arizeaiobservabilityeval/aio/__init__.py
azure/mgmt/arizeaiobservabilityeval/aio/_client.py
azure/mgmt/arizeaiobservabilityeval/aio/_configuration.py
azure/mgmt/arizeaiobservabilityeval/aio/_patch.py
azure/mgmt/arizeaiobservabilityeval/aio/operations/__init__.py
azure/mgmt/arizeaiobservabilityeval/aio/operations/_operations.py
azure/mgmt/arizeaiobservabilityeval/aio/operations/_patch.py
azure/mgmt/arizeaiobservabilityeval/models/__init__.py
azure/mgmt/arizeaiobservabilityeval/models/_enums.py
azure/mgmt/arizeaiobservabilityeval/models/_models.py
azure/mgmt/arizeaiobservabilityeval/models/_patch.py
azure/mgmt/arizeaiobservabilityeval/operations/__init__.py
azure/mgmt/arizeaiobservabilityeval/operations/_operations.py
azure/mgmt/arizeaiobservabilityeval/operations/_patch.py
azure_mgmt_arizeaiobservabilityeval-1.0.0.dist-info/LICENSE
azure_mgmt_arizeaiobservabilityeval-1.0.0.dist-info/METADATA
azure_mgmt_arizeaiobservabilityeval-1.0.0.dist-info/WHEEL
azure_mgmt_arizeaiobservabilityeval-1.0.0.dist-info/top_level.txt
azure_mgmt_arizeaiobservabilityeval-1.0.0.dist-info/RECORD
